{"data":{"user":{"name":"Ahmed Almory","bio":"Backend Engineer","isHireable":true,"avatarUrl":"https://avatars.githubusercontent.com/u/40957053?u=60b0165ad377893553805e4580af0800a696f384&v=4","location":null,"pinnedItems":{"totalCount":2,"edges":[{"node":{"name":"joda-resources","description":null,"forkCount":1,"stargazers":{"totalCount":4},"url":"https://github.com/ahmedalmory/joda-resources","id":"MDEwOlJlcG9zaXRvcnkzODIzMTkyOTg=","diskUsage":33,"primaryLanguage":{"name":"PHP","color":"#4F5D95"}}},{"node":{"name":"clean-code-php","description":":bathtub: Clean Code concepts adapted for PHP","forkCount":3,"stargazers":{"totalCount":13},"url":"https://github.com/ahmedalmory/clean-code-php","id":"R_kgDOGcfVfA","diskUsage":414,"primaryLanguage":{"name":"PHP","color":"#4F5D95"}}}]}}}}